tensorflow_sparse_conv_ops/__init__.py
tensorflow_sparse_conv_ops/_sparse_conv_ops.so
tensorflow_sparse_conv_ops/sparse_conv_ops.py
tensorflow_sparse_conv_ops-0.0.4.dist-info/METADATA
tensorflow_sparse_conv_ops-0.0.4.dist-info/WHEEL
tensorflow_sparse_conv_ops-0.0.4.dist-info/top_level.txt
tensorflow_sparse_conv_ops-0.0.4.dist-info/RECORD
